nonebot/adapters/llbds/__init__.py
nonebot/adapters/llbds/adapter.py
nonebot/adapters/llbds/bot.py
nonebot/adapters/llbds/config.py
nonebot/adapters/llbds/event.py
nonebot/adapters/llbds/exception.py
nonebot/adapters/llbds/log.py
nonebot/adapters/llbds/message.py
nonebot/adapters/llbds/model.py
nonebot/adapters/llbds/store.py
nonebot_adapter_llbds-0.1.2.dist-info/METADATA
nonebot_adapter_llbds-0.1.2.dist-info/WHEEL
nonebot_adapter_llbds-0.1.2.dist-info/licenses/LICENSE
nonebot_adapter_llbds-0.1.2.dist-info/RECORD
