Metadata-Version: 2.1
Name: nonebot-adapter-llbds
Version: 0.1.2
Summary: NoneBot2 LLBDS适配器 / LLBDS Adapter for NoneBot2
Author-Email: zhaomaoniu <2667292003@qq.com>
License: MIT
Requires-Python: >=3.8
Requires-Dist: nonebot2>=2.1.2
